<?xml version="1.0" standalone="no"?>
<!DOCTYPE entity PUBLIC "-//UC Berkeley//DTD MoML 1//EN"
    "http://ptolemy.eecs.berkeley.edu/xml/dtd/MoML_1.dtd">
<entity name="SmartHome" class="ptolemy.actor.TypedCompositeActor">
    <property name="_createdBy" class="ptolemy.kernel.attributes.VersionAttribute" value="11.0.1">
    </property>
    <property name="_windowProperties" class="ptolemy.actor.gui.WindowPropertiesAttribute" value="{bounds={-9, -9, 1938, 1038}, maximized=true}">
    </property>
    <property name="_vergilSize" class="ptolemy.actor.gui.SizeAttribute" value="[1708, 908]">
    </property>
    <property name="_vergilZoomFactor" class="ptolemy.data.expr.ExpertParameter" value="1.0">
    </property>
    <property name="_vergilCenter" class="ptolemy.data.expr.ExpertParameter" value="{844.0, 444.0}">
    </property>
    <property name="WirelessDirector" class="ptolemy.domains.wireless.kernel.WirelessDirector">
        <property name="stopTime" class="ptolemy.data.expr.Parameter" value="47">
        </property>
        <property name="_location" class="ptolemy.kernel.util.Location" value="[175.0, 120.0]">
        </property>
    </property>
    <entity name="homeChannel" class="ptolemy.domains.wireless.kernel.AtomicWirelessChannel">
        <property name="_location" class="ptolemy.kernel.util.Location" value="[415.0, 125.0]">
        </property>
    </entity>
    <entity name="TimeManager" class="ptolemy.domains.wireless.kernel.WirelessComposite">
        <property name="DEDirector" class="ptolemy.domains.de.kernel.DEDirector">
            <property name="_location" class="ptolemy.kernel.util.Location" value="[70.0, 35.0]">
            </property>
        </property>
        <property name="_location" class="ptolemy.kernel.util.Location" value="{410.0, 445.0}">
        </property>
        <port name="output" class="ptolemy.domains.wireless.kernel.WirelessIOPort">
            <property name="output"/>
            <property name="outsideChannel" class="ptolemy.data.expr.StringParameter" value="homeChannel">
            </property>
            <property name="insideChannel" class="ptolemy.data.expr.StringParameter" value="">
            </property>
            <property name="_location" class="ptolemy.kernel.util.Location" value="[755.0, 475.0]">
            </property>
        </port>
        <entity name="DiscreteClock" class="ptolemy.actor.lib.DiscreteClock">
            <property name="stopTime" class="ptolemy.data.expr.Parameter" value="47">
            </property>
            <property name="period" class="ptolemy.actor.parameters.PortParameter" value="1.0">
            </property>
            <doc>Create periodic timed events.</doc>
            <property name="_location" class="ptolemy.kernel.util.Location" value="[40.0, 475.0]">
            </property>
        </entity>
        <entity name="Ramp" class="ptolemy.actor.lib.Ramp">
            <property name="firingCountLimit" class="ptolemy.data.expr.Parameter" value="48">
            </property>
            <doc>Create a sequence of tokens with increasing value</doc>
            <property name="_location" class="ptolemy.kernel.util.Location" value="[180.0, 475.0]">
            </property>
        </entity>
        <entity name="Expression" class="ptolemy.actor.lib.Expression">
            <property name="expression" class="ptolemy.kernel.util.StringAttribute" value="(input * 0.5) - floor(input * 0.5 / 24) * 24">
            </property>
            <property name="_icon" class="ptolemy.vergil.icon.BoxedValueIcon">
                <property name="attributeName" class="ptolemy.kernel.util.StringAttribute" value="expression">
                </property>
                <property name="displayWidth" class="ptolemy.data.expr.Parameter" value="60">
                </property>
                <property name="displayHeight" class="ptolemy.data.expr.Parameter" value="10">
                </property>
            </property>
            <property name="_location" class="ptolemy.kernel.util.Location" value="[380.0, 475.0]">
            </property>
            <port name="input" class="ptolemy.actor.TypedIOPort">
                <property name="input"/>
            </port>
        </entity>
        <entity name="RecordAssembler" class="ptolemy.actor.lib.RecordAssembler">
            <property name="_location" class="ptolemy.kernel.util.Location" value="[625.0, 455.0]">
            </property>
            <port name="timeOfDay" class="ptolemy.actor.TypedIOPort">
                <property name="input"/>
                <property name="_showName" class="ptolemy.data.expr.SingletonParameter" value="true">
                </property>
            </port>
        </entity>
        <entity name="Display2" class="ptolemy.actor.lib.gui.Display">
            <property name="_windowProperties" class="ptolemy.actor.gui.WindowPropertiesAttribute" value="{bounds={1391, 310, 483, 259}, maximized=false}">
            </property>
            <property name="_paneSize" class="ptolemy.actor.gui.SizeAttribute" value="[465, 186]">
            </property>
            <property name="_location" class="ptolemy.kernel.util.Location" value="[705.0, 630.0]">
            </property>
        </entity>
        <entity name="Display" class="ptolemy.actor.lib.gui.Display">
            <property name="_windowProperties" class="ptolemy.actor.gui.WindowPropertiesAttribute" value="{bounds={567, 357, 457, 259}, maximized=false}">
            </property>
            <property name="_paneSize" class="ptolemy.actor.gui.SizeAttribute" value="[439, 186]">
            </property>
            <property name="_location" class="ptolemy.kernel.util.Location" value="[565.0, 635.0]">
            </property>
        </entity>
        <relation name="relation" class="ptolemy.actor.TypedIORelation">
        </relation>
        <relation name="relation2" class="ptolemy.actor.TypedIORelation">
        </relation>
        <relation name="relation5" class="ptolemy.actor.TypedIORelation">
            <property name="width" class="ptolemy.data.expr.Parameter" value="-1">
                <property name="_editorFactory" class="ptolemy.vergil.toolbox.VisibleParameterEditorFactory">
                </property>
            </property>
            <vertex name="vertex" value="{0.0, 0.0}">
            </vertex>
            <vertex name="vertex1" value="{551.8950376884422, 475.43291143216084}">
            </vertex>
        </relation>
        <relation name="relation3" class="ptolemy.actor.TypedIORelation">
            <property name="width" class="ptolemy.data.expr.Parameter" value="-1">
            </property>
            <vertex name="vertex1" value="{686.9350376884422, 474.15291143216086}">
            </vertex>
        </relation>
        <link port="output" relation="relation3"/>
        <link port="DiscreteClock.output" relation="relation"/>
        <link port="Ramp.output" relation="relation2"/>
        <link port="Ramp.trigger" relation="relation"/>
        <link port="Expression.output" relation="relation5"/>
        <link port="Expression.input" relation="relation2"/>
        <link port="RecordAssembler.output" relation="relation3"/>
        <link port="RecordAssembler.timeOfDay" relation="relation5"/>
    </entity>
    <entity name="MotionSensor" class="ptolemy.domains.wireless.kernel.WirelessComposite">
        <property name="DEDirector" class="ptolemy.domains.de.kernel.DEDirector">
            <property name="_location" class="ptolemy.kernel.util.Location" value="[70.0, 35.0]">
            </property>
        </property>
        <property name="_location" class="ptolemy.kernel.util.Location" value="{470.0, 605.0}">
        </property>
        <port name="motion" class="ptolemy.domains.wireless.kernel.WirelessIOPort">
            <property name="output"/>
            <property name="outsideChannel" class="ptolemy.data.expr.StringParameter" value="motionChannel">
            </property>
            <property name="insideChannel" class="ptolemy.data.expr.StringParameter" value="">
            </property>
            <property name="_location" class="ptolemy.kernel.util.Location" value="[815.0, 275.0]">
            </property>
            <property name="_showName" class="ptolemy.data.expr.SingletonParameter" value="true">
            </property>
        </port>
        <port name="input" class="ptolemy.domains.wireless.kernel.WirelessIOPort">
            <property name="input"/>
            <property name="outsideChannel" class="ptolemy.data.expr.StringParameter" value="homeChannel">
            </property>
            <property name="insideChannel" class="ptolemy.data.expr.StringParameter" value="">
            </property>
            <property name="_location" class="ptolemy.kernel.util.Location" value="[85.0, 265.0]">
            </property>
            <property name="_showName" class="ptolemy.data.expr.SingletonParameter" value="true">
            </property>
        </port>
        <entity name="RecordDisassembler" class="ptolemy.actor.lib.RecordDisassembler">
            <property name="_location" class="ptolemy.kernel.util.Location" value="[225.0, 250.0]">
            </property>
            <port name="timeOfDay" class="ptolemy.actor.TypedIOPort">
                <property name="output"/>
                <property name="defaultValue" class="ptolemy.data.expr.Parameter">
                </property>
                <property name="_showName" class="ptolemy.data.expr.SingletonParameter" value="true">
                </property>
            </port>
        </entity>
        <entity name="Expression" class="ptolemy.actor.lib.Expression">
            <property name="expression" class="ptolemy.kernel.util.StringAttribute" value="(timeOfDay &gt;= 7.0 &amp;&amp; timeOfDay &lt; 23.0) ? &#10;  (random() &lt; 0.7 ? true : false) : &#10;  false">
            </property>
            <property name="_icon" class="ptolemy.vergil.icon.BoxedValueIcon">
                <property name="attributeName" class="ptolemy.kernel.util.StringAttribute" value="expression">
                </property>
                <property name="displayWidth" class="ptolemy.data.expr.Parameter" value="60">
                </property>
                <property name="displayHeight" class="ptolemy.data.expr.Parameter" value="10">
                </property>
            </property>
            <property name="_location" class="ptolemy.kernel.util.Location" value="[455.0, 275.0]">
            </property>
            <port name="timeOfDay" class="ptolemy.actor.TypedIOPort">
                <property name="input"/>
                <property name="defaultValue" class="ptolemy.data.expr.Parameter">
                </property>
                <property name="_showName" class="ptolemy.data.expr.SingletonParameter" value="true">
                </property>
            </port>
        </entity>
        <entity name="RecordAssembler" class="ptolemy.actor.lib.RecordAssembler">
            <property name="_location" class="ptolemy.kernel.util.Location" value="[685.0, 255.0]">
            </property>
            <port name="motion" class="ptolemy.actor.TypedIOPort">
                <property name="input"/>
                <property name="defaultValue" class="ptolemy.data.expr.Parameter">
                </property>
            </port>
        </entity>
        <entity name="Display" class="ptolemy.actor.lib.gui.Display">
            <property name="_windowProperties" class="ptolemy.actor.gui.WindowPropertiesAttribute" value="{bounds={777, 410, 365, 259}, maximized=false}">
            </property>
            <property name="_paneSize" class="ptolemy.actor.gui.SizeAttribute" value="[347, 186]">
            </property>
            <property name="_location" class="ptolemy.kernel.util.Location" value="[785.0, 380.0]">
            </property>
        </entity>
        <relation name="relation" class="ptolemy.actor.TypedIORelation">
        </relation>
        <relation name="relation2" class="ptolemy.actor.TypedIORelation">
        </relation>
        <relation name="relation4" class="ptolemy.actor.TypedIORelation">
        </relation>
        <relation name="relation3" class="ptolemy.actor.TypedIORelation">
        </relation>
        <link port="motion" relation="relation3"/>
        <link port="input" relation="relation"/>
        <link port="RecordDisassembler.input" relation="relation"/>
        <link port="RecordDisassembler.timeOfDay" relation="relation2"/>
        <link port="Expression.output" relation="relation4"/>
        <link port="Expression.timeOfDay" relation="relation2"/>
        <link port="RecordAssembler.output" relation="relation3"/>
        <link port="RecordAssembler.motion" relation="relation4"/>
    </entity>
    <entity name="CentralController" class="ptolemy.domains.wireless.kernel.WirelessComposite">
        <property name="DEDirector" class="ptolemy.domains.de.kernel.DEDirector">
            <property name="_location" class="ptolemy.kernel.util.Location" value="[70.0, 35.0]">
            </property>
        </property>
        <property name="_location" class="ptolemy.kernel.util.Location" value="[605.0, 295.0]">
        </property>
        <port name="time" class="ptolemy.domains.wireless.kernel.WirelessIOPort">
            <property name="input"/>
            <property name="outsideChannel" class="ptolemy.data.expr.StringParameter" value="homeChannel">
            </property>
            <property name="insideChannel" class="ptolemy.data.expr.StringParameter" value="">
            </property>
            <property name="_location" class="ptolemy.kernel.util.Location" value="{20.0, 200.0}">
            </property>
            <property name="_showName" class="ptolemy.data.expr.SingletonParameter" value="true">
            </property>
        </port>
        <port name="output" class="ptolemy.domains.wireless.kernel.WirelessIOPort">
            <property name="output"/>
            <property name="outsideChannel" class="ptolemy.data.expr.StringParameter" value="homeChannel">
            </property>
            <property name="insideChannel" class="ptolemy.data.expr.StringParameter" value="">
            </property>
            <property name="_location" class="ptolemy.kernel.util.Location" value="{580.0, 200.0}">
            </property>
        </port>
        <port name="motion" class="ptolemy.domains.wireless.kernel.WirelessIOPort">
            <property name="input"/>
            <property name="defaultValue" class="ptolemy.data.expr.Parameter">
            </property>
            <property name="outsideChannel" class="ptolemy.data.expr.StringParameter" value="motionChannel">
            </property>
            <property name="outsideTransmitProperties" class="ptolemy.data.expr.Parameter">
            </property>
            <property name="insideChannel" class="ptolemy.data.expr.StringParameter" value="">
            </property>
            <property name="insideTransmitProperties" class="ptolemy.data.expr.Parameter">
            </property>
            <property name="_showName" class="ptolemy.data.expr.SingletonParameter" value="true">
            </property>
            <property name="_location" class="ptolemy.kernel.util.Location" value="[20.0, 155.0]">
            </property>
        </port>
        <port name="extTemp" class="ptolemy.domains.wireless.kernel.WirelessIOPort">
            <property name="input"/>
            <property name="defaultValue" class="ptolemy.data.expr.Parameter">
            </property>
            <property name="outsideChannel" class="ptolemy.data.expr.StringParameter" value="">
            </property>
            <property name="outsideTransmitProperties" class="ptolemy.data.expr.Parameter">
            </property>
            <property name="insideChannel" class="ptolemy.data.expr.StringParameter" value="">
            </property>
            <property name="insideTransmitProperties" class="ptolemy.data.expr.Parameter">
            </property>
            <property name="_showName" class="ptolemy.data.expr.SingletonParameter" value="true">
            </property>
            <property name="_location" class="ptolemy.kernel.util.Location" value="{20.0, 240.0}">
            </property>
        </port>
        <port name="intTemp" class="ptolemy.domains.wireless.kernel.WirelessIOPort">
            <property name="input"/>
            <property name="defaultValue" class="ptolemy.data.expr.Parameter">
            </property>
            <property name="outsideChannel" class="ptolemy.data.expr.StringParameter" value="">
            </property>
            <property name="outsideTransmitProperties" class="ptolemy.data.expr.Parameter">
            </property>
            <property name="insideChannel" class="ptolemy.data.expr.StringParameter" value="">
            </property>
            <property name="insideTransmitProperties" class="ptolemy.data.expr.Parameter">
            </property>
            <property name="_showName" class="ptolemy.data.expr.SingletonParameter" value="true">
            </property>
            <property name="_location" class="ptolemy.kernel.util.Location" value="{20.0, 280.0}">
            </property>
        </port>
        <entity name="Display" class="ptolemy.actor.lib.gui.Display">
            <property name="_windowProperties" class="ptolemy.actor.gui.WindowPropertiesAttribute" value="{bounds={1062, 414, 365, 259}, maximized=false}">
            </property>
            <property name="_paneSize" class="ptolemy.actor.gui.SizeAttribute" value="[347, 186]">
            </property>
            <property name="_location" class="ptolemy.kernel.util.Location" value="{260, 165}">
            </property>
        </entity>
        <entity name="Display2" class="ptolemy.actor.lib.gui.Display">
            <property name="_windowProperties" class="ptolemy.actor.gui.WindowPropertiesAttribute" value="{bounds={695, 411, 365, 259}, maximized=false}">
            </property>
            <property name="_paneSize" class="ptolemy.actor.gui.SizeAttribute" value="[347, 186]">
            </property>
            <property name="_location" class="ptolemy.kernel.util.Location" value="{230, 260}">
            </property>
        </entity>
        <relation name="relation" class="ptolemy.actor.TypedIORelation">
        </relation>
        <relation name="relation2" class="ptolemy.actor.TypedIORelation">
        </relation>
        <link port="time" relation="relation2"/>
        <link port="motion" relation="relation"/>
        <link port="Display.input" relation="relation"/>
        <link port="Display2.input" relation="relation2"/>
    </entity>
    <entity name="ExternalTempSensor" class="ptolemy.domains.wireless.kernel.WirelessComposite">
        <property name="DEDirector" class="ptolemy.domains.de.kernel.DEDirector">
            <property name="_location" class="ptolemy.kernel.util.Location" value="[70.0, 35.0]">
            </property>
        </property>
        <property name="_location" class="ptolemy.kernel.util.Location" value="[815.0, 445.0]">
        </property>
        <port name="output" class="ptolemy.domains.wireless.kernel.WirelessIOPort">
            <property name="output"/>
            <property name="outsideChannel" class="ptolemy.data.expr.StringParameter" value="homeChannel">
            </property>
            <property name="insideChannel" class="ptolemy.data.expr.StringParameter" value="">
            </property>
            <property name="_location" class="ptolemy.kernel.util.Location" value="{580.0, 200.0}">
            </property>
        </port>
    </entity>
    <entity name="InternalTempSensor" class="ptolemy.domains.wireless.kernel.WirelessComposite">
        <property name="DEDirector" class="ptolemy.domains.de.kernel.DEDirector">
            <property name="_location" class="ptolemy.kernel.util.Location" value="[70.0, 35.0]">
            </property>
        </property>
        <property name="_location" class="ptolemy.kernel.util.Location" value="[705.0, 620.0]">
        </property>
        <port name="output" class="ptolemy.domains.wireless.kernel.WirelessIOPort">
            <property name="output"/>
            <property name="outsideChannel" class="ptolemy.data.expr.StringParameter" value="homeChannel">
            </property>
            <property name="insideChannel" class="ptolemy.data.expr.StringParameter" value="">
            </property>
        </port>
        <port name="input" class="ptolemy.domains.wireless.kernel.WirelessIOPort">
            <property name="input"/>
            <property name="outsideChannel" class="ptolemy.data.expr.StringParameter" value="">
            </property>
            <property name="insideChannel" class="ptolemy.data.expr.StringParameter" value="">
            </property>
        </port>
    </entity>
    <entity name="motionChannel" class="ptolemy.domains.wireless.kernel.AtomicWirelessChannel">
        <property name="_location" class="ptolemy.kernel.util.Location" value="{530, 130}">
        </property>
    </entity>
</entity>
